saluslux/__init__.py
saluslux/photometry.py
saluslux/simulation.py
saluslux-0.1.0.dist-info/licenses/LICENSE
saluslux-0.1.0.dist-info/METADATA
saluslux-0.1.0.dist-info/WHEEL
saluslux-0.1.0.dist-info/top_level.txt
saluslux-0.1.0.dist-info/RECORD
