Metadata-Version: 2.4
Name: saluslux
Version: 0.1.0
Summary: A Python package for simulating and optimizing urban lighting using photometric data
Author: Korawich Kavee
Author-email: kkavee@andrew.cmu.edu
Classifier: Programming Language :: Python :: 3
Classifier: License :: OSI Approved :: Apache Software License
Classifier: Operating System :: OS Independent
Requires-Python: >=3.8
License-File: LICENSE
Requires-Dist: numpy
Requires-Dist: scipy
Requires-Dist: matplotlib
Requires-Dist: pandas
Dynamic: author
Dynamic: author-email
Dynamic: classifier
Dynamic: license-file
Dynamic: requires-dist
Dynamic: requires-python
Dynamic: summary
